Workbook

Sheet Benefit Summary
A1: QMA GenAI Benefits — Executive Back-of-Envelope Summary
A2: Core story: Against an implementation budget of approximately $600K, the QMA GenAI platform is projected to deliver approximately $11M in annual business benefit through intelligent routing, document automation, EDGE Assist, semantic search and operational insights.
A4: Annual Benefit Target | C4: Equivalent FTEs | E4: Hours Saved / Year | G4: Avg Seconds Saved / Email
A5: =Assumptions!B9 | C5: =Assumptions!B10 | E5: =Assumptions!B11 | G5: =Assumptions!B12
A6: 2026 steady-state | C6: Target benefit ÷ loaded cost/FTE | E6: FTEs × productive hours | G6: Across projected 2026 volume
A9: Three-Year Benefit Projection
A10: Year | B10: Projected QMA Volume | C10: Annual Benefit | D10: FTE Equivalent | E10: Hours Saved
A11: 2026 | B11: =Assumptions!B6 | C11: =Assumptions!B9 | D11: =C11/Assumptions!$B$8 | E11: =D11*Assumptions!$B$7
A12: 2027 | B12: =B11*(1+Assumptions!$B$5) | C12: =C11*(1+Assumptions!$B$5) | D12: =C12/Assumptions!$B$8 | E12: =D12*Assumptions!$B$7
A13: 2028 | B13: =B12*(1+Assumptions!$B$5) | C13: =C12*(1+Assumptions!$B$5) | D13: =C13/Assumptions!$B$8 | E13: =D13*Assumptions!$B$7
A14: 3-Year Total | C14: =SUM(C11:C13) | E14: =SUM(E11:E13)
A16: Note: $3.4M × 3 years = $10.2M flat. Applying the 8.5% annual volume-growth assumption gives about $11.1M over 2026–2028, which reconciles to the stated ~$11M three-year benefit.
A19: Feature-Level Annual Benefit Allocation
A20: Sr No | B20: Feature | C20: Annual Benefit | D20: FTE Equivalent | E20: Visual allocation
A21: =Back_of_Envelope!A5 | B21: =Back_of_Envelope!B5 | C21: =Back_of_Envelope!C5 | D21: =Back_of_Envelope!F5 | E21: =REPT("█",ROUND(Back_of_Envelope!D5*50,0))
A22: =Back_of_Envelope!A6 | B22: =Back_of_Envelope!B6 | C22: =Back_of_Envelope!C6 | D22: =Back_of_Envelope!F6 | E22: =REPT("█",ROUND(Back_of_Envelope!D6*50,0))
A23: =Back_of_Envelope!A7 | B23: =Back_of_Envelope!B7 | C23: =Back_of_Envelope!C7 | D23: =Back_of_Envelope!F7 | E23: =REPT("█",ROUND(Back_of_Envelope!D7*50,0))
A24: =Back_of_Envelope!A8 | B24: =Back_of_Envelope!B8 | C24: =Back_of_Envelope!C8 | D24: =Back_of_Envelope!F8 | E24: =REPT("█",ROUND(Back_of_Envelope!D8*50,0))
A25: =Back_of_Envelope!A9 | B25: =Back_of_Envelope!B9 | C25: =Back_of_Envelope!C9 | D25: =Back_of_Envelope!F9 | E25: =REPT("█",ROUND(Back_of_Envelope!D9*50,0))
A26: =Back_of_Envelope!A10 | B26: =Back_of_Envelope!B10 | C26: =Back_of_Envelope!C10 | D26: =Back_of_Envelope!F10 | E26: =REPT("█",ROUND(Back_of_Envelope!D10*50,0))
A27: =Back_of_Envelope!A11 | B27: =Back_of_Envelope!B11 | C27: =Back_of_Envelope!C11 | D27: =Back_of_Envelope!F11 | E27: =REPT("█",ROUND(Back_of_Envelope!D11*50,0))
B28: Total | C28: =SUM(C21:C27) | D28: =SUM(D21:D27)
A31: Recommended Benefit Driver Mapping
A32: Feature Group | B32: Benefit | C32: Benefit Driver | D32: Measure Type | E32: Unit Measure
A33: Routing / Auto Suggest | B33: Driving Efficiency | C33: Client Experience + Process Efficiency | D33: Manual Touchpoints | E33: #
A34: Document Classification / STP | B34: Driving Efficiency | C34: Process Efficiency | D34: Manual Touchpoints | E34: #
A35: EDGE Assist / Smart Search | B35: Driving Efficiency | C35: Client Experience | D35: Other qualitative value + hours saved | E35: hours
A36: Topic Modeling / QMA Insights | B36: Driving Efficiency | C36: Client Experience | D36: Customer Satisfaction / NPS / VOC + process themes | E36: % / themes
A37: Annualized FTE Benefit | B37: Delivering Financial Impact | C37: Operational Expense Savings/Efficiency | D37: Expense Savings / Head Count | E37: $ / FTE
G38: Investment Metrics
G39: Project Budget | H39: 600000
G40: Projected Annual Benefit | H40: 11000000
G41: Benefit : Cost Ratio | H41: =H40/H39
G42: ROI Multiple | H42: =H41

Sheet Back_of_Envelope
A1: QMA GenAI Benefits — Feature-Level Back-of-Envelope Calculation
A2: Purpose: translate the $3.4M annual target into hours, FTEs and feature-level benefit. Change assumptions or allocation percentages to refresh all values.
A4: Sr No | B4: Main Feature Description | C4: Recommended Saving due to Feature | D4: Allocation of $3.4M Target | E4: Hours Saved / Year | F4: FTE Equivalent | G4: Cumulative FTEs | H4: % of 2026 QMA Volume Touched | I4: Touched Emails / Events / Year | J4: Required Avg Seconds Saved / Touched Event | K4: Saving Mechanism / BOE Rationale | L4: Validation Evidence Needed
A5: 1 | B5: Intent Classification + Auto Suggest routing | C5: =D5*Assumptions!$B$9 | D5: 0.29 | E5: =C5/Assumptions!$B$8*Assumptions!$B$7 | F5: =E5/Assumptions!$B$7 | G5: =SUM($F$5:F5) | H5: 0.035 | I5: =H5*Assumptions!$B$6 | J5: =IF(I5=0,0,E5*3600/I5) | K5: Classify incoming QMA intent and recommend the correct operational queue/group so fewer emails are manually triaged, forwarded, or reworked. | L5: Routing accuracy by intent, % emails auto-suggested, manual reroute rate, before/after triage handling time.
A6: 2 | B6: EDGE Assist summaries + trading/reference data + fail insights | C6: =D6*Assumptions!$B$9 | D6: 0.23 | E6: =C6/Assumptions!$B$8*Assumptions!$B$7 | F6: =E6/Assumptions!$B$7 | G6: =SUM($F$5:F6) | H6: 0.015 | I6: =H6*Assumptions!$B$6 | J6: =IF(I6=0,0,E6*3600/I6) | K6: Summarize long email threads and enrich with trading systems/reference data/fail insights so analysts spend less time reading and reconciling facts. | L6: Average thread review time, assisted cases, analyst acceptance rate, reduction in back-and-forth.
A7: 3 | B7: Document & email classification for invoice processing | C7: =D7*Assumptions!$B$9 | D7: 0.13 | E7: =C7/Assumptions!$B$8*Assumptions!$B$7 | F7: =E7/Assumptions!$B$7 | G7: =SUM($F$5:F7) | H7: 0.002 | I7: =H7*Assumptions!$B$6 | J7: =IF(I7=0,0,E7*3600/I7) | K7: Classify attachments, isolate invoices, pair invoice/summary documents and prepare downstream case creation. | L7: Invoice volume, document classification accuracy, pairing accuracy, manual touch time avoided per invoice.
A8: 4 | B8: Business Process Straight-Through Processing / case creation | C8: =D8*Assumptions!$B$9 | D8: 0.1 | E8: =C8/Assumptions!$B$8*Assumptions!$B$7 | F8: =E8/Assumptions!$B$7 | G8: =SUM($F$5:F8) | H8: 0.0015 | I8: =H8*Assumptions!$B$6 | J8: =IF(I8=0,0,E8*3600/I8) | K8: Automate repeatable routing/case-creation steps where intent, documents and operational ownership are unambiguous. | L8: STP eligible volumes, exception rate, case creation time, manual fallback volumes.
A9: 5 | B9: Smart Search using semantic search | C9: =D9*Assumptions!$B$9 | D9: 0.09 | E9: =C9/Assumptions!$B$8*Assumptions!$B$7 | F9: =E9/Assumptions!$B$7 | G9: =SUM($F$5:F9) | H9: 0.01 | I9: =H9*Assumptions!$B$6 | J9: =IF(I9=0,0,E9*3600/I9) | K9: Allow analysts to find relevant prior emails, cases, entities and themes through semantic search instead of keyword/manual mailbox search. | L9: Search usage, click-through, time-to-find evidence, reduction in repeated requests.
A10: 6 | B10: Margin Calls notification automation | C10: =D10*Assumptions!$B$9 | D10: 0.08 | E10: =C10/Assumptions!$B$8*Assumptions!$B$7 | F10: =E10/Assumptions!$B$7 | G10: =SUM($F$5:F10) | H10: 0.0012 | I10: =H10*Assumptions!$B$6 | J10: =IF(I10=0,0,E10*3600/I10) | K10: Classify margin-related messages, detect notification context and trigger the correct operational workflow/draft response. | L10: Margin email volume, notification accuracy, manual drafting time avoided, exception rate.
A11: 7 | B11: Topic Modeling + QMA Insights | C11: =D11*Assumptions!$B$9 | D11: 0.08 | E11: =C11/Assumptions!$B$8*Assumptions!$B$7 | F11: =E11/Assumptions!$B$7 | G11: =SUM($F$5:F11) | H11: 0.005 | I11: =H11*Assumptions!$B$6 | J11: =IF(I11=0,0,E11*3600/I11) | K11: Cluster email themes in an unsupervised manner to identify where operations spends time and prioritize process redesign and automation. | L11: Cluster quality, top themes by volume/AHT, actions from insights, realized process-change benefit.
B12: Total / Reconciled to Target | C12: =SUM(C5:C11) | D12: =SUM(D5:D11) | E12: =SUM(E5:E11) | F12: =SUM(F5:F11) | G12: =F12 | I12: =SUM(I5:I11) | J12: =IF(I12=0,0,E12*3600/I12) | K12: Total reconciles to the $3.4M annual benefit target.

Sheet Assumptions
A1: QMA GenAI Benefit Back-of-Envelope Assumptions
A3: Input / Assumption | B3: Value | C3: Unit | D3: Purpose / Note
A4: Base unique QMA/email volume | B4: 31000000 | C4: emails/events in 2025 | D4: User-provided baseline. Treat as unique email/events, not every message touch.
A5: Annual volume growth | B5: 0.085 | C5: % YoY | D5: User-provided growth expectation. Used for 2026+ projection.
A6: Projected unique QMA/email volume | B6: =B4*(1+B5) | C6: emails/events in 2026 | D6: Formula: 2025 volume × (1 + growth).
A7: Effective productive hours per FTE | B7: 1800 | C7: hours/year | D7: BOE assumption; adjust to your finance standard if different.
A8: Fully loaded Ops cost per FTE | B8: 225000 | C8: $/FTE/year | D8: BOE assumption; includes salary, benefits, occupancy, management overhead.
A9: Target annual benefit | B9: 11000000 | C9: $ in 2026 | D9: Updated annual realized projected benefit
A10: Target FTE equivalent | B10: =B9/B8 | C10: FTEs | D10: Formula: target annual benefit ÷ loaded Ops cost/FTE.
A11: Target hours saved | B11: =B10*B7 | C11: hours/year | D11: Formula: FTE equivalent × hours/FTE.
A12: Average seconds saved needed across all 2026 emails | B12: =B11*3600/B6 | C12: seconds/email | D12: Small average efficiency across large volume can generate material benefit.
A13: Stated 3-year target | B13: 11000000 | C13: $ over 3 years | D13: User-provided headline target.
A14: Flat 3-year value at 2026 target | B14: =B9*3 | C14: $ over 3 years | D14: $3.4M × 3 = $10.2M; useful conservative view.
A15: Growth-adjusted 3-year value | B15: =B9*(1+(1+B5)+(1+B5)^2) | C15: $ over 3 years | D15: Applies 8.5% YoY growth to annual benefit.
A16: Variance to stated 3-year target | B16: =B15-B13 | C16: $ | D16: Positive means growth-adjusted case exceeds stated target.
A18: Source notes: Updated business case - Project budget $600K; realized/projected annual benefit $11M.
